[{"Code": "MENI00214", "Title": "Insurance", "Icon": "", "Link": "/pages/report/Insurance", "Sequence": "7", "Click": "", "Menu": "MENU0005", "Submenu": "", "Permission": "InsuranceRto.reports_insurance", "Created On": "2022-11-08 12:37:01", "Modified On": "2023-01-10 13:06:41", "Created By": "", "Modified By": ""}, {"Code": "MENI00211", "Title": "Zone", "Icon": "", "Link": "Zone", "Sequence": "100", "Click": "1", "Menu": "MENU0007", "Submenu": "", "Permission": "Masters.import_zone", "Created On": "2022-11-05 13:13:08", "Modified On": "2023-01-10 13:06:41", "Created By": "", "Modified By": ""}, {"Code": "MENI00218", "Title": "My Stock", "Icon": "0xe183", "Link": "/myStockView", "Sequence": "100", "Click": "/myStockView", "Menu": "MENU0001", "Submenu": "SMENU0004", "Permission": "Purchase.view_stock", "Created On": "2022-12-21 07:05:19", "Modified On": "2023-01-10 13:06:41", "Created By": "", "Modified By": ""}, {"Code": "MIM01155", "Title": "Repair Amount", "Icon": "0xe23d", "Link": "/repairAmountList", "Sequence": "100", "Click": "/repairAmountList", "Menu": "MENU0001", "Submenu": "SMENU0004", "Permission": "StockTransfer.view_repairamount", "Created On": "2022-12-26 05:27:46", "Modified On": "2023-01-10 13:06:41", "Created By": "", "Modified By": ""}, {"Code": "MENI00112", "Title": "User", "Icon": "", "Link": "Employee", "Sequence": "100", "Click": "", "Menu": "MENU0009", "Submenu": "", "Permission": "Masters.export_employee", "Created On": "2022-11-05 13:13:08", "Modified On": "2023-01-10 13:06:41", "Created By": "", "Modified By": ""}, {"Code": "MENI00219", "Title": "My Stock", "Icon": "HistoryOutlined", "Link": "/pages/mystock", "Sequence": "4", "Click": "", "Menu": "MENU0004", "Submenu": "", "Permission": "Purchase.view_stock", "Created On": "2023-01-02 07:01:34", "Modified On": "2023-01-10 13:06:41", "Created By": "", "Modified By": ""}, {"Code": "MENI00143", "Title": "StockTransferIn", "Icon": "", "Link": "StockTransferIn", "Sequence": "100", "Click": "", "Menu": "MENU0009", "Submenu": "", "Permission": "StockTransfer.export_stocktransfer", "Created On": "2022-11-05 13:13:08", "Modified On": "2023-01-10 13:06:41", "Created By": "", "Modified By": ""}, {"Code": "MENI00023", "Title": "Leave Reasons", "Icon": "", "Link": "/Masters/leavereasons", "Sequence": "12", "Click": "", "Menu": "MENU0003", "Submenu": "", "Permission": "Masters.view_leavereason", "Created On": "2022-11-05 13:13:08", "Modified On": "2023-01-10 13:06:41", "Created By": "", "Modified By": ""}, {"Code": "MENI00022", "Title": "Insurance", "Icon": "", "Link": "/Masters/insurance", "Sequence": "100", "Click": "", "Menu": "MENU0003", "Submenu": "", "Permission": "Masters.view_insurancecompany", "Created On": "2022-11-05 13:13:08", "Modified On": "2023-01-10 13:06:41", "Created By": "", "Modified By": ""}, {"Code": "MENI00021", "Title": "Emidates", "Icon": "", "Link": "/Masters/emidates", "Sequence": "100", "Click": "", "Menu": "MENU0003", "Submenu": "", "Permission": "Masters.view_emidate", "Created On": "2022-11-05 13:13:08", "Modified On": "2023-01-10 13:06:41", "Created By": "", "Modified By": ""}, {"Code": "MENI00020", "Title": "Dealers", "Icon": "", "Link": "/Masters/dealers", "Sequence": "14", "Click": "", "Menu": "MENU0003", "Submenu": "", "Permission": "Masters.view_dealer", "Created On": "2022-11-05 13:13:08", "Modified On": "2023-01-10 13:06:41", "Created By": "", "Modified By": ""}, {"Code": "MENI00172", "Title": "Device", "Icon": "", "Link": "Device", "Sequence": "100", "Click": "1", "Menu": "MENU0007", "Submenu": "", "Permission": "Users.import_device", "Created On": "2022-11-05 13:13:08", "Modified On": "2023-01-10 13:06:41", "Created By": "", "Modified By": ""}, {"Code": "MENI00171", "Title": "Department", "Icon": "", "Link": "Department", "Sequence": "100", "Click": "1", "Menu": "MENU0007", "Submenu": "", "Permission": "Masters.import_department", "Created On": "2022-11-05 13:13:08", "Modified On": "2023-01-10 13:06:41", "Created By": "", "Modified By": ""}, {"Code": "MENI00170", "Title": "Dealer", "Icon": "", "Link": "Dealer", "Sequence": "100", "Click": "1", "Menu": "MENU0007", "Submenu": "", "Permission": "Masters.import_dealer", "Created On": "2022-11-05 13:13:08", "Modified On": "2023-01-10 13:06:41", "Created By": "", "Modified By": ""}, {"Code": "MENI00169", "Title": "Country", "Icon": "", "Link": "Country", "Sequence": "100", "Click": "1", "Menu": "MENU0007", "Submenu": "", "Permission": "Masters.import_country", "Created On": "2022-11-05 13:13:08", "Modified On": "2023-01-10 13:06:41", "Created By": "", "Modified By": ""}, {"Code": "MENI00168", "Title": "Counter", "Icon": "", "Link": "Counter", "Sequence": "100", "Click": "1", "Menu": "MENU0007", "Submenu": "", "Permission": "Masters.import_counter", "Created On": "2022-11-05 13:13:08", "Modified On": "2023-01-10 13:06:41", "Created By": "", "Modified By": ""}, {"Code": "MENI00167", "Title": "CompanyBank", "Icon": "", "Link": "CompanyBank", "Sequence": "100", "Click": "1", "Menu": "MENU0007", "Submenu": "", "Permission": "Masters.import_companybank", "Created On": "2022-11-05 13:13:08", "Modified On": "2023-01-10 13:06:41", "Created By": "", "Modified By": ""}, {"Code": "MENI00165", "Title": "Cluster", "Icon": "", "Link": "Cluster", "Sequence": "100", "Click": "1", "Menu": "MENU0007", "Submenu": "", "Permission": "Masters.import_cluster", "Created On": "2022-11-05 13:13:08", "Modified On": "2023-01-10 13:06:41", "Created By": "", "Modified By": ""}, {"Code": "MENI00164", "Title": "City", "Icon": "", "Link": "City", "Sequence": "100", "Click": "1", "Menu": "MENU0007", "Submenu": "", "Permission": "Masters.import_city", "Created On": "2022-11-05 13:13:08", "Modified On": "2023-01-10 13:06:41", "Created By": "", "Modified By": ""}, {"Code": "MENI00163", "Title": "BrandFamily", "Icon": "", "Link": "BrandFamily", "Sequence": "100", "Click": "1", "Menu": "MENU0007", "Submenu": "", "Permission": "Masters.import_brandfamily", "Created On": "2022-11-05 13:13:08", "Modified On": "2023-01-10 13:06:41", "Created By": "", "Modified By": ""}, {"Code": "MENI00162", "Title": "Brand", "Icon": "", "Link": "Brand", "Sequence": "100", "Click": "1", "Menu": "MENU0007", "Submenu": "", "Permission": "Masters.import_brand", "Created On": "2022-11-05 13:13:08", "Modified On": "2023-01-10 13:06:41", "Created By": "", "Modified By": ""}, {"Code": "MENI00161", "Title": "Bank", "Icon": "", "Link": "Bank", "Sequence": "100", "Click": "1", "Menu": "MENU0007", "Submenu": "", "Permission": "Masters.import_bank", "Created On": "2022-11-05 13:13:08", "Modified On": "2023-01-10 13:06:41", "Created By": "", "Modified By": ""}, {"Code": "MENI00160", "Title": "Backup", "Icon": "", "Link": "Backup", "Sequence": "100", "Click": "1", "Menu": "MENU0007", "Submenu": "", "Permission": "System.import_backup", "Created On": "2022-11-05 13:13:08", "Modified On": "2023-01-10 13:06:41", "Created By": "", "Modified By": ""}, {"Code": "MENI00159", "Title": "Area", "Icon": "", "Link": "Area", "Sequence": "100", "Click": "1", "Menu": "MENU0007", "Submenu": "", "Permission": "Masters.import_area", "Created On": "2022-11-05 13:13:08", "Modified On": "2023-01-10 13:06:41", "Created By": "", "Modified By": ""}, {"Code": "MENI00158", "Title": "AddressProof", "Icon": "", "Link": "AddressProof", "Sequence": "100", "Click": "1", "Menu": "MENU0007", "Submenu": "", "Permission": "Masters.import_addressproof", "Created On": "2022-11-05 13:13:08", "Modified On": "2023-01-10 13:06:41", "Created By": "", "Modified By": ""}, {"Code": "MENI00157", "Title": "Zone", "Icon": "", "Link": "Zone", "Sequence": "100", "Click": "", "Menu": "MENU0009", "Submenu": "", "Permission": "Masters.export_zone", "Created On": "2022-11-05 13:13:08", "Modified On": "2023-01-10 13:06:41", "Created By": "", "Modified By": ""}, {"Code": "MENI00156", "Title": "VersionFeature", "Icon": "", "Link": "VersionFeature", "Sequence": "100", "Click": "", "Menu": "MENU0009", "Submenu": "", "Permission": "Masters.export_versionfeature", "Created On": "2022-11-05 13:13:08", "Modified On": "2023-01-10 13:06:41", "Created By": "", "Modified By": ""}, {"Code": "MENI00155", "Title": "Version", "Icon": "", "Link": "Version", "Sequence": "100", "Click": "", "Menu": "MENU0009", "Submenu": "", "Permission": "Masters.export_version", "Created On": "2022-11-05 13:13:08", "Modified On": "2023-01-10 13:06:41", "Created By": "", "Modified By": ""}, {"Code": "MENI00154", "Title": "VehicleType", "Icon": "", "Link": "VehicleType", "Sequence": "100", "Click": "", "Menu": "MENU0009", "Submenu": "", "Permission": "Masters.export_vehicletype", "Created On": "2022-11-05 13:13:08", "Modified On": "2023-01-10 13:06:41", "Created By": "", "Modified By": ""}, {"Code": "MENI00153", "Title": "VehicleEstimation", "Icon": "", "Link": "VehicleEstimation", "Sequence": "100", "Click": "", "Menu": "MENU0009", "Submenu": "", "Permission": "Purchase.export_vehicleestimation", "Created On": "2022-11-05 13:13:08", "Modified On": "2023-01-10 13:06:41", "Created By": "", "Modified By": ""}, {"Code": "MENI00025", "Title": "Reject Reasons", "Icon": "", "Link": "/Masters/rejectreasons", "Sequence": "100", "Click": "", "Menu": "MENU0003", "Submenu": "", "Permission": "Masters.view_rejectreason", "Created On": "2022-11-05 13:13:08", "Modified On": "2023-01-10 13:06:41", "Created By": "", "Modified By": ""}, {"Code": "MENI00024", "Title": "Version Features", "Icon": "", "Link": "/Masters/versionfeatures", "Sequence": "36", "Click": "", "Menu": "MENU0003", "Submenu": "", "Permission": "Masters.view_versionfeature", "Created On": "2022-11-05 13:13:08", "Modified On": "2023-01-10 13:06:41", "Created By": "", "Modified By": ""}, {"Code": "MENI00204", "Title": "TestDrive", "Icon": "", "Link": "TestDrive", "Sequence": "100", "Click": "1", "Menu": "MENU0007", "Submenu": "", "Permission": "StockTransfer.import_testdrive", "Created On": "2022-11-05 13:13:08", "Modified On": "2023-01-10 13:06:41", "Created By": "", "Modified By": ""}, {"Code": "MENI00202", "Title": "Submenu", "Icon": "", "Link": "Submenu", "Sequence": "100", "Click": "1", "Menu": "MENU0007", "Submenu": "", "Permission": "System.import_submenu", "Created On": "2022-11-05 13:13:08", "Modified On": "2023-01-10 13:06:41", "Created By": "", "Modified By": ""}, {"Code": "MENI00201", "Title": "StockTransferOut", "Icon": "", "Link": "StockTransferOut", "Sequence": "100", "Click": "1", "Menu": "MENU0007", "Submenu": "", "Permission": "StockTransfer.import_stocktransfer", "Created On": "2022-11-05 13:13:08", "Modified On": "2023-01-10 13:06:41", "Created By": "", "Modified By": ""}, {"Code": "MENI00200", "Title": "StockTransferIn", "Icon": "", "Link": "StockTransferIn", "Sequence": "100", "Click": "1", "Menu": "MENU0007", "Submenu": "", "Permission": "StockTransfer.import_stocktransfer", "Created On": "2022-11-05 13:13:08", "Modified On": "2023-01-10 13:06:41", "Created By": "", "Modified By": ""}, {"Code": "MENI00199", "Title": "State", "Icon": "", "Link": "State", "Sequence": "100", "Click": "1", "Menu": "MENU0007", "Submenu": "", "Permission": "Masters.import_state", "Created On": "2022-11-05 13:13:08", "Modified On": "2023-01-10 13:06:41", "Created By": "", "Modified By": ""}, {"Code": "MENI00198", "Title": "ShowRoom", "Icon": "", "Link": "ShowRoom", "Sequence": "100", "Click": "1", "Menu": "MENU0007", "Submenu": "", "Permission": "Masters.import_showroom", "Created On": "2022-11-05 13:13:08", "Modified On": "2023-01-10 13:06:41", "Created By": "", "Modified By": ""}, {"Code": "MENI00197", "Title": "Sale", "Icon": "", "Link": "Sale", "Sequence": "100", "Click": "1", "Menu": "MENU0007", "Submenu": "", "Permission": "Sale.import_sale", "Created On": "2022-11-05 13:13:08", "Modified On": "2023-01-10 13:06:41", "Created By": "", "Modified By": ""}, {"Code": "MENI00196", "Title": "RepairVechicle", "Icon": "", "Link": "RepairVechicle", "Sequence": "100", "Click": "1", "Menu": "MENU0007", "Submenu": "", "Permission": "StockTransfer.import_repairvechicle", "Created On": "2022-11-05 13:13:08", "Modified On": "2023-01-10 13:06:41", "Created By": "", "Modified By": ""}, {"Code": "MENI00195", "Title": "RepairAmount", "Icon": "", "Link": "RepairAmount", "Sequence": "100", "Click": "1", "Menu": "MENU0007", "Submenu": "", "Permission": "StockTransfer.import_repairamount", "Created On": "2022-11-05 13:13:08", "Modified On": "2023-01-10 13:06:41", "Created By": "", "Modified By": ""}, {"Code": "MENI00194", "Title": "RejectReason", "Icon": "", "Link": "RejectReason", "Sequence": "100", "Click": "1", "Menu": "MENU0007", "Submenu": "", "Permission": "Masters.import_rejectreason", "Created On": "2022-11-05 13:13:08", "Modified On": "2023-01-10 13:06:41", "Created By": "", "Modified By": ""}, {"Code": "MENI00193", "Title": "ReEstimatonAmount", "Icon": "", "Link": "ReEstimatonAmount", "Sequence": "100", "Click": "1", "Menu": "MENU0007", "Submenu": "", "Permission": "StockTransfer.import_reestimatonamount", "Created On": "2022-11-05 13:13:08", "Modified On": "2023-01-10 13:06:41", "Created By": "", "Modified By": ""}, {"Code": "MENI00192", "Title": "PurchaseApproval", "Icon": "", "Link": "PurchaseApproval", "Sequence": "100", "Click": "1", "Menu": "MENU0007", "Submenu": "", "Permission": "Purchase.import_purchaseapproval", "Created On": "2022-11-05 13:13:08", "Modified On": "2023-01-10 13:06:41", "Created By": "", "Modified By": ""}, {"Code": "MENI00190", "Title": "Priority", "Icon": "", "Link": "Priority", "Sequence": "100", "Click": "1", "Menu": "MENU0007", "Submenu": "", "Permission": "Masters.import_priority", "Created On": "2022-11-05 13:13:08", "Modified On": "2023-01-10 13:06:41", "Created By": "", "Modified By": ""}, {"Code": "MENI00189", "Title": "PersonAddressVersion", "Icon": "", "Link": "PersonAddressVersion", "Sequence": "100", "Click": "1", "Menu": "MENU0007", "Submenu": "", "Permission": "Masters.import_personaddressversion", "Created On": "2022-11-05 13:13:08", "Modified On": "2023-01-10 13:06:41", "Created By": "", "Modified By": ""}, {"Code": "MENI00187", "Title": "Opening Stock", "Icon": "", "Link": "Opening Stock", "Sequence": "100", "Click": "1", "Menu": "MENU0007", "Submenu": "", "Permission": "StockTransfer.import_stocktransfer", "Created On": "2022-11-05 13:13:08", "Modified On": "2023-01-10 13:06:41", "Created By": "", "Modified By": ""}, {"Code": "MENI00186", "Title": "Occupation", "Icon": "", "Link": "Occupation", "Sequence": "100", "Click": "1", "Menu": "MENU0007", "Submenu": "", "Permission": "Masters.import_occupation", "Created On": "2022-11-05 13:13:08", "Modified On": "2023-01-10 13:06:41", "Created By": "", "Modified By": ""}, {"Code": "MENI00185", "Title": "Notification", "Icon": "", "Link": "Notification", "Sequence": "100", "Click": "1", "Menu": "MENU0007", "Submenu": "", "Permission": "System.import_notification", "Created On": "2022-11-05 13:13:08", "Modified On": "2023-01-10 13:06:41", "Created By": "", "Modified By": ""}, {"Code": "MENI00184", "Title": "Model", "Icon": "", "Link": "Model", "Sequence": "100", "Click": "1", "Menu": "MENU0007", "Submenu": "", "Permission": "Masters.import_model", "Created On": "2022-11-05 13:13:08", "Modified On": "2023-01-10 13:06:41", "Created By": "", "Modified By": ""}, {"Code": "MENI00183", "Title": "Menuitem", "Icon": "", "Link": "Menuitem", "Sequence": "100", "Click": "1", "Menu": "MENU0007", "Submenu": "", "Permission": "System.import_menuitem", "Created On": "2022-11-05 13:13:08", "Modified On": "2023-01-10 13:06:41", "Created By": "", "Modified By": ""}, {"Code": "MENI00182", "Title": "Menu", "Icon": "", "Link": "Menu", "Sequence": "100", "Click": "1", "Menu": "MENU0007", "Submenu": "", "Permission": "System.import_menu", "Created On": "2022-11-05 13:13:08", "Modified On": "2023-01-10 13:06:41", "Created By": "", "Modified By": ""}, {"Code": "MENI00181", "Title": "Mechanic", "Icon": "", "Link": "Mechanic", "Sequence": "100", "Click": "1", "Menu": "MENU0007", "Submenu": "", "Permission": "Masters.import_mechanic", "Created On": "2022-11-05 13:13:08", "Modified On": "2023-01-10 13:06:41", "Created By": "", "Modified By": ""}, {"Code": "MENI00180", "Title": "LeaveReason", "Icon": "", "Link": "LeaveReason", "Sequence": "100", "Click": "1", "Menu": "MENU0007", "Submenu": "", "Permission": "Masters.import_leavereason", "Created On": "2022-11-05 13:13:08", "Modified On": "2023-01-10 13:06:41", "Created By": "", "Modified By": ""}, {"Code": "MENI00179", "Title": "InsuranceCompany", "Icon": "", "Link": "InsuranceCompany", "Sequence": "100", "Click": "1", "Menu": "MENU0007", "Submenu": "", "Permission": "Masters.import_insurancecompany", "Created On": "2022-11-05 13:13:08", "Modified On": "2023-01-10 13:06:41", "Created By": "", "Modified By": ""}, {"Code": "MENI00178", "Title": "Firm", "Icon": "", "Link": "Firm", "Sequence": "100", "Click": "1", "Menu": "MENU0007", "Submenu": "", "Permission": "Masters.import_firm", "Created On": "2022-11-05 13:13:08", "Modified On": "2023-01-10 13:06:41", "Created By": "", "Modified By": ""}, {"Code": "MENI00177", "Title": "Financier", "Icon": "", "Link": "Financier", "Sequence": "100", "Click": "1", "Menu": "MENU0007", "Submenu": "", "Permission": "Masters.import_financier", "Created On": "2022-11-05 13:13:08", "Modified On": "2023-01-10 13:06:41", "Created By": "", "Modified By": ""}, {"Code": "MENI00152", "Title": "VehicleAttendance", "Icon": "", "Link": "VehicleAttendance", "Sequence": "100", "Click": "", "Menu": "MENU0009", "Submenu": "", "Permission": "Attendance.export_vehicleattendance", "Created On": "2022-11-05 13:13:08", "Modified On": "2023-01-10 13:06:41", "Created By": "", "Modified By": ""}, {"Code": "MENI00079", "Title": "Repair Types", "Icon": "", "Link": "/Masters/Repair-Types", "Sequence": "92", "Click": "", "Menu": "MENU0003", "Submenu": "", "Permission": "Masters.view_repair", "Created On": "2022-11-05 13:13:08", "Modified On": "2023-01-10 13:06:41", "Created By": "", "Modified By": ""}, {"Code": "MENI00151", "Title": "Vehicle", "Icon": "", "Link": "Vehicle", "Sequence": "100", "Click": "", "Menu": "MENU0009", "Submenu": "", "Permission": "Masters.export_vehicle", "Created On": "2022-11-05 13:13:08", "Modified On": "2023-01-10 13:06:41", "Created By": "", "Modified By": ""}, {"Code": "MENI00150", "Title": "UserAddressVersion", "Icon": "", "Link": "UserAddressVersion", "Sequence": "100", "Click": "", "Menu": "MENU0009", "Submenu": "", "Permission": "Users.export_useraddressversion", "Created On": "2022-11-05 13:13:08", "Modified On": "2023-01-10 13:06:41", "Created By": "", "Modified By": ""}, {"Code": "MENI00148", "Title": "TimeSheet", "Icon": "", "Link": "TimeSheet", "Sequence": "100", "Click": "", "Menu": "MENU0009", "Submenu": "", "Permission": "Attendance.export_timesheet", "Created On": "2022-11-05 13:13:08", "Modified On": "2023-01-10 13:06:41", "Created By": "", "Modified By": ""}, {"Code": "MENI00147", "Title": "TestDrive", "Icon": "", "Link": "TestDrive", "Sequence": "100", "Click": "", "Menu": "MENU0009", "Submenu": "", "Permission": "StockTransfer.export_testdrive", "Created On": "2022-11-05 13:13:08", "Modified On": "2023-01-10 13:06:41", "Created By": "", "Modified By": ""}, {"Code": "MENI00146", "Title": "TemporaryTransfer", "Icon": "", "Link": "TemporaryTransfer", "Sequence": "100", "Click": "", "Menu": "MENU0009", "Submenu": "", "Permission": "StockTransfer.export_temprarorytransfer", "Created On": "2022-11-05 13:13:08", "Modified On": "2023-01-10 13:06:42", "Created By": "", "Modified By": ""}, {"Code": "MENI00019", "Title": "Address Proof", "Icon": "", "Link": "/Masters/addressproof", "Sequence": "13", "Click": "", "Menu": "MENU0003", "Submenu": "", "Permission": "Masters.view_addressproof", "Created On": "2022-11-05 13:13:08", "Modified On": "2023-01-10 13:06:41", "Created By": "", "Modified By": ""}, {"Code": "MENI00018", "Title": "Brand Family", "Icon": "", "Link": "/Masters/brandfamily", "Sequence": "32", "Click": "", "Menu": "MENU0003", "Submenu": "", "Permission": "Masters.view_brandfamily", "Created On": "2022-11-05 13:13:08", "Modified On": "2023-01-10 13:06:41", "Created By": "", "Modified By": ""}, {"Code": "MENI00017", "Title": "Clusters", "Icon": "", "Link": "/Masters/clusters", "Sequence": "9", "Click": "", "Menu": "MENU0003", "Submenu": "", "Permission": "Masters.view_cluster", "Created On": "2022-11-05 13:13:09", "Modified On": "2023-01-10 13:06:41", "Created By": "", "Modified By": ""}, {"Code": "MENI00016", "Title": "Divisions", "Icon": "", "Link": "/Masters/divisions", "Sequence": "8", "Click": "", "Menu": "MENU0003", "Submenu": "", "Permission": "Masters.view_division", "Created On": "2022-11-05 13:13:09", "Modified On": "2023-01-10 13:06:41", "Created By": "", "Modified By": ""}, {"Code": "MENI00015", "Title": "Company Banks", "Icon": "", "Link": "/Masters/companybanks", "Sequence": "100", "Click": "", "Menu": "MENU0003", "Submenu": "", "Permission": "Masters.view_companybank", "Created On": "2022-11-05 13:13:09", "Modified On": "2023-01-10 13:06:41", "Created By": "", "Modified By": ""}, {"Code": "MENI00014", "Title": "Priority", "Icon": "", "Link": "/Masters/priority", "Sequence": "35", "Click": "", "Menu": "MENU0003", "Submenu": "", "Permission": "Masters.view_priority", "Created On": "2022-11-05 13:13:09", "Modified On": "2023-01-10 13:06:41", "Created By": "", "Modified By": ""}, {"Code": "MENI00013", "Title": "Banks", "Icon": "", "Link": "/Masters/banks", "Sequence": "100", "Click": "", "Menu": "MENU0003", "Submenu": "", "Permission": "Masters.view_bank", "Created On": "2022-11-05 13:13:09", "Modified On": "2023-01-10 13:06:41", "Created By": "", "Modified By": ""}, {"Code": "MENI00012", "Title": "Colors", "Icon": "", "Link": "/Masters/colors", "Sequence": "100", "Click": "", "Menu": "MENU0003", "Submenu": "", "Permission": "Masters.view_color", "Created On": "2022-11-05 13:13:09", "Modified On": "2023-01-10 13:06:41", "Created By": "", "Modified By": ""}, {"Code": "MENI00011", "Title": "Occupations", "Icon": "", "Link": "/Masters/occupations", "Sequence": "100", "Click": "", "Menu": "MENU0003", "Submenu": "", "Permission": "Masters.view_occupation", "Created On": "2022-11-05 13:13:09", "Modified On": "2023-01-10 13:06:41", "Created By": "", "Modified By": ""}, {"Code": "MENI00010", "Title": "Emissionnorms", "Icon": "", "Link": "/Masters/emissionnorms", "Sequence": "38", "Click": "", "Menu": "MENU0003", "Submenu": "", "Permission": "Masters.view_emissionnorms", "Created On": "2022-11-05 13:13:09", "Modified On": "2023-01-10 13:06:41", "Created By": "", "Modified By": ""}, {"Code": "MENI00009", "Title": "Brand", "Icon": "", "Link": "/Masters/brand", "Sequence": "31", "Click": "", "Menu": "MENU0003", "Submenu": "", "Permission": "Masters.view_brand", "Created On": "2022-11-05 13:13:09", "Modified On": "2023-01-10 13:06:41", "Created By": "", "Modified By": ""}, {"Code": "MENI00008", "Title": "Firm", "Icon": "", "Link": "/Masters/firm", "Sequence": "6", "Click": "", "Menu": "MENU0003", "Submenu": "", "Permission": "Masters.view_firm", "Created On": "2022-11-05 13:13:09", "Modified On": "2023-01-10 13:06:41", "Created By": "", "Modified By": ""}, {"Code": "MENI00007", "Title": "Zone", "Icon": "", "Link": "/Masters/zone", "Sequence": "7", "Click": "", "Menu": "MENU0003", "Submenu": "", "Permission": "Masters.view_zone", "Created On": "2022-11-05 13:13:09", "Modified On": "2023-01-10 13:06:41", "Created By": "", "Modified By": ""}, {"Code": "MENI00006", "Title": "Area", "Icon": "", "Link": "/Masters/Area", "Sequence": "5", "Click": "", "Menu": "MENU0003", "Submenu": "", "Permission": "Masters.view_area", "Created On": "2022-11-05 13:13:09", "Modified On": "2023-01-10 13:06:41", "Created By": "", "Modified By": ""}, {"Code": "MENI00005", "Title": "City", "Icon": "", "Link": "/Masters/City", "Sequence": "4", "Click": "", "Menu": "MENU0003", "Submenu": "", "Permission": "Masters.view_city", "Created On": "2022-11-05 13:13:09", "Modified On": "2023-01-10 13:06:41", "Created By": "", "Modified By": ""}, {"Code": "MENI00004", "Title": "District", "Icon": "", "Link": "/Masters/District", "Sequence": "3", "Click": "", "Menu": "MENU0003", "Submenu": "", "Permission": "Masters.view_district", "Created On": "2022-11-05 13:13:09", "Modified On": "2023-01-10 13:06:41", "Created By": "", "Modified By": ""}, {"Code": "MENI00003", "Title": "Models", "Icon": "", "Link": "/Masters/models", "Sequence": "33", "Click": "", "Menu": "MENU0003", "Submenu": "", "Permission": "Masters.view_model", "Created On": "2022-11-05 13:13:09", "Modified On": "2023-01-10 13:06:41", "Created By": "", "Modified By": ""}, {"Code": "MENI00002", "Title": "State", "Icon": "", "Link": "/Masters/state", "Sequence": "2", "Click": "", "Menu": "MENU0003", "Submenu": "", "Permission": "Masters.view_state", "Created On": "2022-11-05 13:13:09", "Modified On": "2023-01-10 13:06:41", "Created By": "", "Modified By": ""}, {"Code": "MENI00208", "Title": "VehicleType", "Icon": "", "Link": "VehicleType", "Sequence": "100", "Click": "1", "Menu": "MENU0007", "Submenu": "", "Permission": "Masters.import_vehicletype", "Created On": "2022-11-05 13:13:08", "Modified On": "2023-01-10 13:06:41", "Created By": "", "Modified By": ""}, {"Code": "MENI00207", "Title": "Vehicle", "Icon": "", "Link": "Vehicle", "Sequence": "100", "Click": "1", "Menu": "MENU0007", "Submenu": "", "Permission": "Masters.import_vehicle", "Created On": "2022-11-05 13:13:08", "Modified On": "2023-01-10 13:06:41", "Created By": "", "Modified By": ""}, {"Code": "MENI00206", "Title": "UserAddressVersion", "Icon": "", "Link": "UserAddressVersion", "Sequence": "100", "Click": "1", "Menu": "MENU0007", "Submenu": "", "Permission": "Users.import_useraddressversion", "Created On": "2022-11-05 13:13:08", "Modified On": "2023-01-10 13:06:41", "Created By": "", "Modified By": ""}, {"Code": "MENI00026", "Title": "Vehicle Types", "Icon": "", "Link": "/Masters/vehicletypes", "Sequence": "34", "Click": "", "Menu": "MENU0003", "Submenu": "", "Permission": "Masters.view_vehicletype", "Created On": "2022-11-05 13:13:08", "Modified On": "2023-01-10 13:06:41", "Created By": "", "Modified By": ""}, {"Code": "MENI00176", "Title": "Employee", "Icon": "", "Link": "Employee", "Sequence": "100", "Click": "1", "Menu": "MENU0007", "Submenu": "", "Permission": "Masters.import_employee", "Created On": "2022-11-05 13:13:08", "Modified On": "2023-01-10 13:06:41", "Created By": "", "Modified By": ""}, {"Code": "MENI00175", "Title": "EmissionNorms", "Icon": "", "Link": "EmissionNorms", "Sequence": "100", "Click": "1", "Menu": "MENU0007", "Submenu": "", "Permission": "Masters.import_emissionnorms", "Created On": "2022-11-05 13:13:08", "Modified On": "2023-01-10 13:06:41", "Created By": "", "Modified By": ""}, {"Code": "MENI00174", "Title": "Division", "Icon": "", "Link": "Division", "Sequence": "100", "Click": "1", "Menu": "MENU0007", "Submenu": "", "Permission": "Masters.import_division", "Created On": "2022-11-05 13:13:08", "Modified On": "2023-01-10 13:06:41", "Created By": "", "Modified By": ""}, {"Code": "MENI00173", "Title": "District", "Icon": "", "Link": "District", "Sequence": "100", "Click": "1", "Menu": "MENU0007", "Submenu": "", "Permission": "Masters.import_district", "Created On": "2022-11-05 13:13:08", "Modified On": "2023-01-10 13:06:41", "Created By": "", "Modified By": ""}, {"Code": "MENI00188", "Title": "Person", "Icon": "", "Link": "Person", "Sequence": "100", "Click": "1", "Menu": "MENU0007", "Submenu": "", "Permission": "Masters.import_person", "Created On": "2022-11-05 13:13:08", "Modified On": "2023-01-10 13:06:41", "Created By": "", "Modified By": ""}, {"Code": "MENI00166", "Title": "Color", "Icon": "", "Link": "Color", "Sequence": "100", "Click": "1", "Menu": "MENU0007", "Submenu": "", "Permission": "Masters.import_color", "Created On": "2022-11-05 13:13:08", "Modified On": "2023-01-10 13:06:41", "Created By": "", "Modified By": ""}, {"Code": "MENI00128", "Title": "OVFQuotation", "Icon": "", "Link": "OVFQuotation", "Sequence": "100", "Click": "", "Menu": "MENU0009", "Submenu": "", "Permission": "Sale.export_ovfquotation", "Created On": "2022-11-05 13:13:08", "Modified On": "2023-01-10 13:06:42", "Created By": "", "Modified By": ""}, {"Code": "MENI00099", "Title": "City", "Icon": "", "Link": "City", "Sequence": "100", "Click": "", "Menu": "MENU0009", "Submenu": "", "Permission": "Masters.export_city", "Created On": "2022-11-05 13:13:08", "Modified On": "2023-01-10 13:06:42", "Created By": "", "Modified By": ""}, {"Code": "MENI00098", "Title": "BrandFamily", "Icon": "", "Link": "BrandFamily", "Sequence": "100", "Click": "", "Menu": "MENU0009", "Submenu": "", "Permission": "Masters.export_brandfamily", "Created On": "2022-11-05 13:13:08", "Modified On": "2023-01-10 13:06:42", "Created By": "", "Modified By": ""}, {"Code": "MENI00097", "Title": "Brand", "Icon": "", "Link": "Brand", "Sequence": "100", "Click": "", "Menu": "MENU0009", "Submenu": "", "Permission": "Masters.export_brand", "Created On": "2022-11-05 13:13:08", "Modified On": "2023-01-10 13:06:42", "Created By": "", "Modified By": ""}, {"Code": "MENI00096", "Title": "Bank", "Icon": "", "Link": "Bank", "Sequence": "100", "Click": "", "Menu": "MENU0009", "Submenu": "", "Permission": "Masters.export_bank", "Created On": "2022-11-05 13:13:08", "Modified On": "2023-01-10 13:06:42", "Created By": "", "Modified By": ""}, {"Code": "MENI00095", "Title": "Backup", "Icon": "", "Link": "Backup", "Sequence": "100", "Click": "", "Menu": "MENU0009", "Submenu": "", "Permission": "System.export_backup", "Created On": "2022-11-05 13:13:08", "Modified On": "2023-01-10 13:06:42", "Created By": "", "Modified By": ""}, {"Code": "MENI00094", "Title": "Area", "Icon": "", "Link": "Area", "Sequence": "100", "Click": "", "Menu": "MENU0009", "Submenu": "", "Permission": "Masters.export_area", "Created On": "2022-11-05 13:13:08", "Modified On": "2023-01-10 13:06:42", "Created By": "", "Modified By": ""}, {"Code": "MENI00093", "Title": "Approval", "Icon": "", "Link": "Approval", "Sequence": "100", "Click": "", "Menu": "MENU0009", "Submenu": "", "Permission": "Permissions.export_approval", "Created On": "2022-11-05 13:13:08", "Modified On": "2023-01-10 13:06:42", "Created By": "", "Modified By": ""}, {"Code": "MENI00092", "Title": "AddressProof", "Icon": "", "Link": "AddressProof", "Sequence": "100", "Click": "", "Menu": "MENU0009", "Submenu": "", "Permission": "Masters.export_addressproof", "Created On": "2022-11-05 13:13:08", "Modified On": "2023-01-10 13:06:42", "Created By": "", "Modified By": ""}, {"Code": "MENI00081", "Title": "Manage Users", "Icon": "", "Link": "/pages/settings/manage-users", "Sequence": "1", "Click": "", "Menu": "MENU0008", "Submenu": "SMENU0007", "Permission": "Masters.view_employee", "Created On": "2022-11-05 13:13:08", "Modified On": "2023-01-10 13:06:42", "Created By": "", "Modified By": ""}, {"Code": "MENI00084", "Title": "Approvals", "Icon": "", "Link": "/pages/settings/approvals", "Sequence": "3", "Click": "", "Menu": "MENU0008", "Submenu": "SMENU0008", "Permission": "Permissions.view_approval", "Created On": "2022-11-05 13:13:08", "Modified On": "2023-01-10 13:06:42", "Created By": "", "Modified By": ""}, {"Code": "MENI00085", "Title": "App Settings", "Icon": "", "Link": "/pages/settings/app-settings", "Sequence": "7", "Click": "", "Menu": "MENU0008", "Submenu": "SMENU0009", "Permission": "System.view_setting", "Created On": "2022-11-05 13:13:08", "Modified On": "2023-01-10 13:06:42", "Created By": "", "Modified By": ""}, {"Code": "MENI00083", "Title": "Location Managers", "Icon": "", "Link": "/pages/settings/location-manager", "Sequence": "5", "Click": "", "Menu": "MENU0008", "Submenu": "SMENU0008", "Permission": "Permissions.view_locationmanager", "Created On": "2022-11-05 13:13:08", "Modified On": "2023-01-10 13:06:42", "Created By": "", "Modified By": ""}, {"Code": "MENI00089", "Title": "Import", "Icon": "", "Link": "/pages/settings/import-csv", "Sequence": "9", "Click": "", "Menu": "MENU0008", "Submenu": "SMENU0009", "Permission": "System.view_import", "Created On": "2022-11-05 13:13:08", "Modified On": "2023-01-10 13:06:42", "Created By": "", "Modified By": ""}, {"Code": "MENI00082", "Title": "Managers", "Icon": "", "Link": "/pages/settings/managers", "Sequence": "4", "Click": "", "Menu": "MENU0008", "Submenu": "SMENU0008", "Permission": "Permissions.view_manager", "Created On": "2022-11-05 13:13:08", "Modified On": "2023-01-10 13:06:42", "Created By": "", "Modified By": ""}, {"Code": "MENI00086", "Title": "Manage Company", "Icon": "", "Link": "/pages/settings/manage-company", "Sequence": "6", "Click": "", "Menu": "MENU0008", "Submenu": "SMENU0009", "Permission": "System.view_setting", "Created On": "2022-11-05 13:13:08", "Modified On": "2023-01-10 13:06:42", "Created By": "", "Modified By": ""}, {"Code": "MENI00088", "Title": "Backup Database", "Icon": "", "Link": "/pages/settings/backup-database", "Sequence": "8", "Click": "", "Menu": "MENU0008", "Submenu": "SMENU0009", "Permission": "System.view_backup", "Created On": "2022-11-05 13:13:08", "Modified On": "2023-01-10 13:06:42", "Created By": "", "Modified By": ""}, {"Code": "MENI00090", "Title": "Exports", "Icon": "", "Link": "/pages/settings/export-csv", "Sequence": "10", "Click": "", "Menu": "MENU0008", "Submenu": "SMENU0009", "Permission": "System.view_export", "Created On": "2022-11-05 13:13:08", "Modified On": "2023-01-10 13:06:42", "Created By": "", "Modified By": ""}, {"Code": "MENI00076", "Title": "Field Verification", "Icon": "0xe11d", "Link": "/fieldVerificationView", "Sequence": "12", "Click": "/fieldVerificationView", "Menu": "MENU0001", "Submenu": "SMENU0004", "Permission": "Sale.view_fieldverification", "Created On": "2022-11-05 13:13:08", "Modified On": "2023-01-10 13:06:42", "Created By": "", "Modified By": ""}, {"Code": "MENI00075", "Title": "Insurance", "Icon": "0xe1a9", "Link": "/insuranceListView", "Sequence": "7", "Click": "/insuranceListView", "Menu": "MENU0001", "Submenu": "SMENU0004", "Permission": "InsuranceRto.view_insurance", "Created On": "2022-11-05 13:13:08", "Modified On": "2023-01-10 13:06:42", "Created By": "", "Modified By": ""}, {"Code": "MENI00068", "Title": "Purchase", "Icon": "BarChartOutlined", "Link": "/pages/purchases", "Sequence": "1", "Click": "", "Menu": "MENU0006", "Submenu": "", "Permission": "Purchase.view_purchase", "Created On": "2022-11-05 13:13:08", "Modified On": "2023-01-10 13:06:42", "Created By": "", "Modified By": ""}, {"Code": "MENI00028", "Title": "Interest", "Icon": "", "Link": "/Masters/percentageinterests", "Sequence": "100", "Click": "", "Menu": "MENU0003", "Submenu": "", "Permission": "Masters.view_percentageinterest", "Created On": "2022-11-05 13:13:08", "Modified On": "2023-01-10 13:06:42", "Created By": "", "Modified By": ""}, {"Code": "MENI00027", "Title": "Showrooms", "Icon": "", "Link": "/Masters/showrooms", "Sequence": "100", "Click": "", "Menu": "MENU0003", "Submenu": "", "Permission": "Masters.view_showroom", "Created On": "2022-11-05 13:13:08", "Modified On": "2023-01-10 13:06:42", "Created By": "", "Modified By": ""}, {"Code": "MENI00037", "Title": "Sale Quotation", "Icon": "AuditOutlined", "Link": "/pages/sales-quatation-list", "Sequence": "3", "Click": "", "Menu": "MENU0004", "Submenu": "SMENU0001", "Permission": "Sale.view_salequotation", "Created On": "2022-11-05 13:13:08", "Modified On": "2023-01-10 13:06:42", "Created By": "", "Modified By": ""}, {"Code": "MENI00036", "Title": "Sale", "Icon": "PieChartOutlined", "Link": "/pages/Vechicle-Sales", "Sequence": "4", "Click": "", "Menu": "MENU0004", "Submenu": "SMENU0001", "Permission": "Sale.view_sale", "Created On": "2022-11-05 13:13:08", "Modified On": "2023-01-10 13:06:42", "Created By": "", "Modified By": ""}, {"Code": "MENI00042", "Title": "Repairs", "Icon": "ToolOutlined", "Link": "/pages/stock-transfer-repair", "Sequence": "7", "Click": "", "Menu": "MENU0004", "Submenu": "SMENU0002", "Permission": "StockTransfer.view_repairvechicle", "Created On": "2022-11-05 13:13:08", "Modified On": "2023-01-10 13:06:42", "Created By": "", "Modified By": ""}, {"Code": "MENI00038", "Title": "Customers", "Icon": "UsergroupAddOutlined", "Link": "/Masters/person", "Sequence": "11", "Click": "", "Menu": "MENU0004", "Submenu": "", "Permission": "Masters.view_person", "Created On": "2022-11-05 13:13:08", "Modified On": "2023-01-10 13:06:42", "Created By": "", "Modified By": ""}, {"Code": "MENI00074", "Title": "Customer", "Icon": "UsergroupAddOutlined", "Link": "/Masters/person", "Sequence": "5", "Click": "", "Menu": "MENU0006", "Submenu": "", "Permission": "Masters.view_person", "Created On": "2022-11-05 13:13:08", "Modified On": "2023-01-10 13:06:42", "Created By": "", "Modified By": ""}, {"Code": "MENI00073", "Title": "Add Vehicle", "Icon": "DeliveredProcedureOutlined", "Link": "/Masters/vehicles", "Sequence": "4", "Click": "", "Menu": "MENU0006", "Submenu": "", "Permission": "Masters.view_vehicle", "Created On": "2022-11-05 13:13:08", "Modified On": "2023-01-10 13:06:42", "Created By": "", "Modified By": ""}, {"Code": "MENI00070", "Title": "Enquiry", "Icon": "ContactsOutlined", "Link": "/pages/enquiry", "Sequence": "6", "Click": "", "Menu": "MENU0006", "Submenu": "", "Permission": "Purchase.view_enquiry", "Created On": "2022-11-05 13:13:08", "Modified On": "2023-01-10 13:06:42", "Created By": "", "Modified By": ""}, {"Code": "MENI00069", "Title": "Sale", "Icon": "PieChartOutlined", "Link": "/pages/Vechicle-Sales", "Sequence": "2", "Click": "", "Menu": "MENU0006", "Submenu": "", "Permission": "Sale.view_sale", "Created On": "2022-11-05 13:13:08", "Modified On": "2023-01-10 13:06:42", "Created By": "", "Modified By": ""}, {"Code": "MENI00071", "Title": "Sale Quotation", "Icon": "AuditOutlined", "Link": "/pages/sales-quatation-list", "Sequence": "3", "Click": "", "Menu": "MENU0006", "Submenu": "", "Permission": "Sale.view_salequotation", "Created On": "2022-11-05 13:13:08", "Modified On": "2023-01-10 13:06:42", "Created By": "", "Modified By": ""}, {"Code": "MENI00072", "Title": "Repairs", "Icon": "ToolOutlined", "Link": "/pages/stock-transfer-repair", "Sequence": "7", "Click": "", "Menu": "MENU0006", "Submenu": "", "Permission": "StockTransfer.view_repairvechicle", "Created On": "2022-11-05 13:13:08", "Modified On": "2023-01-10 13:06:42", "Created By": "", "Modified By": ""}, {"Code": "MENI00062", "Title": "Stock", "Icon": "ToolOutlined", "Link": "/pages/stock", "Sequence": "3", "Click": "", "Menu": "MENU0004", "Submenu": "", "Permission": "Purchase.view_stock", "Created On": "2022-11-05 13:13:08", "Modified On": "2023-01-10 13:06:42", "Created By": "", "Modified By": ""}, {"Code": "MENI00047", "Title": "RTO", "Icon": "ProfileOutlined", "Link": "/pages/rto", "Sequence": "6", "Click": "", "Menu": "MENU0004", "Submenu": "", "Permission": "InsuranceRto.view_rta", "Created On": "2022-11-05 13:13:08", "Modified On": "2023-01-10 13:06:42", "Created By": "", "Modified By": ""}, {"Code": "MENI00145", "Title": "Submenu", "Icon": "", "Link": "Submenu", "Sequence": "100", "Click": "", "Menu": "MENU0009", "Submenu": "", "Permission": "System.export_submenu", "Created On": "2022-11-05 13:13:08", "Modified On": "2023-01-10 13:06:42", "Created By": "", "Modified By": ""}, {"Code": "MENI00144", "Title": "StockTransferOut", "Icon": "", "Link": "StockTransferOut", "Sequence": "100", "Click": "", "Menu": "MENU0009", "Submenu": "", "Permission": "StockTransfer.export_stocktransfer", "Created On": "2022-11-05 13:13:08", "Modified On": "2023-01-10 13:06:42", "Created By": "", "Modified By": ""}, {"Code": "MENI00142", "Title": "Stock", "Icon": "", "Link": "Stock", "Sequence": "100", "Click": "", "Menu": "MENU0009", "Submenu": "", "Permission": "Purchase.export_stock", "Created On": "2022-11-05 13:13:08", "Modified On": "2023-01-10 13:06:42", "Created By": "", "Modified By": ""}, {"Code": "MENI00141", "Title": "State", "Icon": "", "Link": "State", "Sequence": "100", "Click": "", "Menu": "MENU0009", "Submenu": "", "Permission": "Masters.export_state", "Created On": "2022-11-05 13:13:08", "Modified On": "2023-01-10 13:06:42", "Created By": "", "Modified By": ""}, {"Code": "MENI00140", "Title": "ShowRoom", "Icon": "", "Link": "ShowRoom", "Sequence": "100", "Click": "", "Menu": "MENU0009", "Submenu": "", "Permission": "Masters.export_showroom", "Created On": "2022-11-05 13:13:08", "Modified On": "2023-01-10 13:06:42", "Created By": "", "Modified By": ""}, {"Code": "MENI00139", "Title": "SaleQuotation", "Icon": "", "Link": "SaleQuotation", "Sequence": "100", "Click": "", "Menu": "MENU0009", "Submenu": "", "Permission": "Sale.export_salequotation", "Created On": "2022-11-05 13:13:08", "Modified On": "2023-01-10 13:06:42", "Created By": "", "Modified By": ""}, {"Code": "MENI00138", "Title": "Sale", "Icon": "", "Link": "Sale", "Sequence": "100", "Click": "", "Menu": "MENU0009", "Submenu": "", "Permission": "Sale.export_sale", "Created On": "2022-11-05 13:13:08", "Modified On": "2023-01-10 13:06:42", "Created By": "", "Modified By": ""}, {"Code": "MENI00137", "Title": "RepairVechicle", "Icon": "", "Link": "RepairVechicle", "Sequence": "100", "Click": "", "Menu": "MENU0009", "Submenu": "", "Permission": "StockTransfer.export_repairvechicle", "Created On": "2022-11-05 13:13:08", "Modified On": "2023-01-10 13:06:42", "Created By": "", "Modified By": ""}, {"Code": "MENI00136", "Title": "RepairAmount", "Icon": "", "Link": "RepairAmount", "Sequence": "100", "Click": "", "Menu": "MENU0009", "Submenu": "", "Permission": "StockTransfer.export_repairamount", "Created On": "2022-11-05 13:13:08", "Modified On": "2023-01-10 13:06:42", "Created By": "", "Modified By": ""}, {"Code": "MENI00135", "Title": "RejectReason", "Icon": "", "Link": "RejectReason", "Sequence": "100", "Click": "", "Menu": "MENU0009", "Submenu": "", "Permission": "Masters.export_rejectreason", "Created On": "2022-11-05 13:13:08", "Modified On": "2023-01-10 13:06:42", "Created By": "", "Modified By": ""}, {"Code": "MENI00134", "Title": "ReEstimatonAmount", "Icon": "", "Link": "ReEstimatonAmount", "Sequence": "100", "Click": "", "Menu": "MENU0009", "Submenu": "", "Permission": "StockTransfer.export_reestimatonamount", "Created On": "2022-11-05 13:13:08", "Modified On": "2023-01-10 13:06:42", "Created By": "", "Modified By": ""}, {"Code": "MENI00133", "Title": "PurchaseApproval", "Icon": "", "Link": "PurchaseApproval", "Sequence": "100", "Click": "", "Menu": "MENU0009", "Submenu": "", "Permission": "Purchase.export_purchaseapproval", "Created On": "2022-11-05 13:13:08", "Modified On": "2023-01-10 13:06:42", "Created By": "", "Modified By": ""}, {"Code": "MENI00132", "Title": "Purchase", "Icon": "", "Link": "Purchase", "Sequence": "100", "Click": "", "Menu": "MENU0009", "Submenu": "", "Permission": "Purchase.export_purchase", "Created On": "2022-11-05 13:13:08", "Modified On": "2023-01-10 13:06:42", "Created By": "", "Modified By": ""}, {"Code": "MENI00131", "Title": "Priority", "Icon": "", "Link": "Priority", "Sequence": "100", "Click": "", "Menu": "MENU0009", "Submenu": "", "Permission": "Masters.export_priority", "Created On": "2022-11-05 13:13:08", "Modified On": "2023-01-10 13:06:42", "Created By": "", "Modified By": ""}, {"Code": "MENI00130", "Title": "PersonAddressVersion", "Icon": "", "Link": "PersonAddressVersion", "Sequence": "100", "Click": "", "Menu": "MENU0009", "Submenu": "", "Permission": "Masters.export_personaddressversion", "Created On": "2022-11-05 13:13:08", "Modified On": "2023-01-10 13:06:42", "Created By": "", "Modified By": ""}, {"Code": "MENI00129", "Title": "Person", "Icon": "", "Link": "Person", "Sequence": "100", "Click": "", "Menu": "MENU0009", "Submenu": "", "Permission": "Masters.export_person", "Created On": "2022-11-05 13:13:08", "Modified On": "2023-01-10 13:06:42", "Created By": "", "Modified By": ""}, {"Code": "MENI00127", "Title": "Occupation", "Icon": "", "Link": "Occupation", "Sequence": "100", "Click": "", "Menu": "MENU0009", "Submenu": "", "Permission": "Masters.export_occupation", "Created On": "2022-11-05 13:13:08", "Modified On": "2023-01-10 13:06:42", "Created By": "", "Modified By": ""}, {"Code": "MENI00126", "Title": "Notification", "Icon": "", "Link": "Notification", "Sequence": "100", "Click": "", "Menu": "MENU0009", "Submenu": "", "Permission": "System.export_notification", "Created On": "2022-11-05 13:13:08", "Modified On": "2023-01-10 13:06:42", "Created By": "", "Modified By": ""}, {"Code": "MENI00125", "Title": "Model", "Icon": "", "Link": "Model", "Sequence": "100", "Click": "", "Menu": "MENU0009", "Submenu": "", "Permission": "Masters.export_model", "Created On": "2022-11-05 13:13:08", "Modified On": "2023-01-10 13:06:42", "Created By": "", "Modified By": ""}, {"Code": "MENI00123", "Title": "Menu", "Icon": "", "Link": "Menu", "Sequence": "100", "Click": "", "Menu": "MENU0009", "Submenu": "", "Permission": "System.export_menu", "Created On": "2022-11-05 13:13:08", "Modified On": "2023-01-10 13:06:42", "Created By": "", "Modified By": ""}, {"Code": "MENI00122", "Title": "Mechanic", "Icon": "", "Link": "Mechanic", "Sequence": "100", "Click": "", "Menu": "MENU0009", "Submenu": "", "Permission": "Masters.export_mechanic", "Created On": "2022-11-05 13:13:08", "Modified On": "2023-01-10 13:06:42", "Created By": "", "Modified By": ""}, {"Code": "MENI00121", "Title": "Manager", "Icon": "", "Link": "Manager", "Sequence": "100", "Click": "", "Menu": "MENU0009", "Submenu": "", "Permission": "Permissions.export_manager", "Created On": "2022-11-05 13:13:08", "Modified On": "2023-01-10 13:06:42", "Created By": "", "Modified By": ""}, {"Code": "MENI00120", "Title": "LocationManager", "Icon": "", "Link": "LocationManager", "Sequence": "100", "Click": "", "Menu": "MENU0009", "Submenu": "", "Permission": "Permissions.export_locationmanager", "Created On": "2022-11-05 13:13:08", "Modified On": "2023-01-10 13:06:42", "Created By": "", "Modified By": ""}, {"Code": "MENI00119", "Title": "LeaveReason", "Icon": "", "Link": "LeaveReason", "Sequence": "100", "Click": "", "Menu": "MENU0009", "Submenu": "", "Permission": "Masters.export_leavereason", "Created On": "2022-11-05 13:13:08", "Modified On": "2023-01-10 13:06:42", "Created By": "", "Modified By": ""}, {"Code": "MENI00118", "Title": "Leave", "Icon": "", "Link": "Leave", "Sequence": "100", "Click": "", "Menu": "MENU0009", "Submenu": "", "Permission": "Attendance.export_leave", "Created On": "2022-11-05 13:13:08", "Modified On": "2023-01-10 13:06:42", "Created By": "", "Modified By": ""}, {"Code": "MENI00117", "Title": "InsuranceCompany", "Icon": "", "Link": "InsuranceCompany", "Sequence": "100", "Click": "", "Menu": "MENU0009", "Submenu": "", "Permission": "Masters.export_insurancecompany", "Created On": "2022-11-05 13:13:08", "Modified On": "2023-01-10 13:06:42", "Created By": "", "Modified By": ""}, {"Code": "MENI00116", "Title": "HRMS Daily Attendance", "Icon": "", "Link": "HRMS Daily Attendance", "Sequence": "100", "Click": "", "Menu": "MENU0009", "Submenu": "", "Permission": "Attendance.export_dailyattendance", "Created On": "2022-11-05 13:13:08", "Modified On": "2023-01-10 13:06:42", "Created By": "", "Modified By": ""}, {"Code": "MENI00115", "Title": "Firm", "Icon": "", "Link": "Firm", "Sequence": "100", "Click": "", "Menu": "MENU0009", "Submenu": "", "Permission": "Masters.export_firm", "Created On": "2022-11-05 13:13:08", "Modified On": "2023-01-10 13:06:42", "Created By": "", "Modified By": ""}, {"Code": "MENI00114", "Title": "Financier", "Icon": "", "Link": "Financier", "Sequence": "100", "Click": "", "Menu": "MENU0009", "Submenu": "", "Permission": "Masters.export_financier", "Created On": "2022-11-05 13:13:08", "Modified On": "2023-01-10 13:06:42", "Created By": "", "Modified By": ""}, {"Code": "MENI00113", "Title": "Enquiry", "Icon": "", "Link": "Enquiry", "Sequence": "100", "Click": "", "Menu": "MENU0009", "Submenu": "", "Permission": "Purchase.export_enquiry", "Created On": "2022-11-05 13:13:08", "Modified On": "2023-01-10 13:06:42", "Created By": "", "Modified By": ""}, {"Code": "MENI00111", "Title": "EmissionNorms", "Icon": "", "Link": "EmissionNorms", "Sequence": "100", "Click": "", "Menu": "MENU0009", "Submenu": "", "Permission": "Masters.export_emissionnorms", "Created On": "2022-11-05 13:13:08", "Modified On": "2023-01-10 13:06:42", "Created By": "", "Modified By": ""}, {"Code": "MENI00110", "Title": "Division", "Icon": "", "Link": "Division", "Sequence": "100", "Click": "", "Menu": "MENU0009", "Submenu": "", "Permission": "Masters.export_division", "Created On": "2022-11-05 13:13:08", "Modified On": "2023-01-10 13:06:42", "Created By": "", "Modified By": ""}, {"Code": "MENI00109", "Title": "District", "Icon": "", "Link": "District", "Sequence": "100", "Click": "", "Menu": "MENU0009", "Submenu": "", "Permission": "Masters.export_district", "Created On": "2022-11-05 13:13:08", "Modified On": "2023-01-10 13:06:42", "Created By": "", "Modified By": ""}, {"Code": "MENI00108", "Title": "Device", "Icon": "", "Link": "Device", "Sequence": "100", "Click": "", "Menu": "MENU0009", "Submenu": "", "Permission": "Users.export_device", "Created On": "2022-11-05 13:13:08", "Modified On": "2023-01-10 13:06:42", "Created By": "", "Modified By": ""}, {"Code": "MENI00107", "Title": "Department", "Icon": "", "Link": "Department", "Sequence": "100", "Click": "", "Menu": "MENU0009", "Submenu": "", "Permission": "Masters.export_department", "Created On": "2022-11-05 13:13:08", "Modified On": "2023-01-10 13:06:42", "Created By": "", "Modified By": ""}, {"Code": "MENI00106", "Title": "Dealer", "Icon": "", "Link": "Dealer", "Sequence": "100", "Click": "", "Menu": "MENU0009", "Submenu": "", "Permission": "Masters.export_dealer", "Created On": "2022-11-05 13:13:08", "Modified On": "2023-01-10 13:06:42", "Created By": "", "Modified By": ""}, {"Code": "MENI00105", "Title": "Daily Attendance", "Icon": "", "Link": "Daily Attendance", "Sequence": "100", "Click": "", "Menu": "MENU0009", "Submenu": "", "Permission": "Attendance.export_dailyattendance", "Created On": "2022-11-05 13:13:08", "Modified On": "2023-01-10 13:06:42", "Created By": "", "Modified By": ""}, {"Code": "MENI00104", "Title": "Country", "Icon": "", "Link": "Country", "Sequence": "100", "Click": "", "Menu": "MENU0009", "Submenu": "", "Permission": "Masters.export_country", "Created On": "2022-11-05 13:13:08", "Modified On": "2023-01-10 13:06:42", "Created By": "", "Modified By": ""}, {"Code": "MENI00103", "Title": "Counter", "Icon": "", "Link": "Counter", "Sequence": "100", "Click": "", "Menu": "MENU0009", "Submenu": "", "Permission": "Masters.export_counter", "Created On": "2022-11-05 13:13:08", "Modified On": "2023-01-10 13:06:42", "Created By": "", "Modified By": ""}, {"Code": "MENI00102", "Title": "CompanyBank", "Icon": "", "Link": "CompanyBank", "Sequence": "100", "Click": "", "Menu": "MENU0009", "Submenu": "", "Permission": "Masters.export_companybank", "Created On": "2022-11-05 13:13:08", "Modified On": "2023-01-10 13:06:42", "Created By": "", "Modified By": ""}, {"Code": "MENI00101", "Title": "Color", "Icon": "", "Link": "Color", "Sequence": "100", "Click": "", "Menu": "MENU0009", "Submenu": "", "Permission": "Masters.export_color", "Created On": "2022-11-05 13:13:08", "Modified On": "2023-01-10 13:06:42", "Created By": "", "Modified By": ""}, {"Code": "MENI00100", "Title": "Cluster", "Icon": "", "Link": "Cluster", "Sequence": "100", "Click": "", "Menu": "MENU0009", "Submenu": "", "Permission": "Masters.export_cluster", "Created On": "2022-11-05 13:13:08", "Modified On": "2023-01-10 13:06:42", "Created By": "", "Modified By": ""}, {"Code": "MENI00066", "Title": "Temporary Stock List", "Icon": "0xe2ad", "Link": "/stockTransferListView", "Sequence": "5", "Click": "/stockTransferListView", "Menu": "MENU0001", "Submenu": "SMENU0004", "Permission": "StockTransfer.view_repairvechicle", "Created On": "2022-11-05 13:13:08", "Modified On": "2023-01-10 13:06:42", "Created By": "", "Modified By": ""}, {"Code": "MENI00065", "Title": "Sale List", "Icon": "0xe20e", "Link": "/saleList", "Sequence": "4", "Click": "/saleList", "Menu": "MENU0001", "Submenu": "SMENU0004", "Permission": "Sale.view_sale", "Created On": "2022-11-05 13:13:08", "Modified On": "2023-01-10 13:06:42", "Created By": "", "Modified By": ""}, {"Code": "MENI00064", "Title": "Purchase List", "Icon": "0xe033", "Link": "/purchaseListView", "Sequence": "3", "Click": "/purchaseListView", "Menu": "MENU0001", "Submenu": "SMENU0004", "Permission": "Purchase.view_purchase", "Created On": "2022-11-05 13:13:08", "Modified On": "2023-01-10 13:06:42", "Created By": "", "Modified By": ""}, {"Code": "MENI00063", "Title": "Quotation List", "Icon": "0xe02d", "Link": "/quotationsListView", "Sequence": "2", "Click": "/quotationsListView", "Menu": "MENU0001", "Submenu": "SMENU0004", "Permission": "Sale.view_salequotation", "Created On": "2022-11-05 13:13:08", "Modified On": "2023-01-10 13:06:42", "Created By": "", "Modified By": ""}, {"Code": "MENI00053", "Title": "Enquiries List", "Icon": "0xe0a6", "Link": "/salesEnquiryListView", "Sequence": "1", "Click": "/salesEnquiryListView", "Menu": "MENU0001", "Submenu": "SMENU0004", "Permission": "Purchase.view_enquiry", "Created On": "2022-11-05 13:13:08", "Modified On": "2023-01-10 13:06:42", "Created By": "", "Modified By": ""}, {"Code": "MENI00052", "Title": "FV-Questions", "Icon": "", "Link": "/Masters/fv-questions", "Sequence": "100", "Click": "", "Menu": "MENU0003", "Submenu": "", "Permission": "Masters.view_fieldverificationquestions", "Created On": "2022-11-05 13:13:08", "Modified On": "2023-01-10 13:06:42", "Created By": "", "Modified By": ""}, {"Code": "MENI00034", "Title": "Departments", "Icon": "", "Link": "/Masters/Departments", "Sequence": "11", "Click": "", "Menu": "MENU0003", "Submenu": "", "Permission": "Masters.view_department", "Created On": "2022-11-05 13:13:08", "Modified On": "2023-01-10 13:06:42", "Created By": "", "Modified By": ""}, {"Code": "MENI00033", "Title": "Vehicles", "Icon": "", "Link": "/Masters/vehicles", "Sequence": "39", "Click": "", "Menu": "MENU0003", "Submenu": "", "Permission": "Masters.view_vehicle", "Created On": "2022-11-05 13:13:08", "Modified On": "2023-01-10 13:06:42", "Created By": "", "Modified By": ""}, {"Code": "MENI00032", "Title": "Versions", "Icon": "", "Link": "/Masters/versions", "Sequence": "37", "Click": "", "Menu": "MENU0003", "Submenu": "", "Permission": "Masters.view_version", "Created On": "2022-11-05 13:13:08", "Modified On": "2023-01-10 13:06:42", "Created By": "", "Modified By": ""}, {"Code": "MENI00031", "Title": "Counters", "Icon": "", "Link": "/Masters/Counters", "Sequence": "10", "Click": "", "Menu": "MENU0003", "Submenu": "", "Permission": "Masters.view_counter", "Created On": "2022-11-05 13:13:08", "Modified On": "2023-01-10 13:06:42", "Created By": "", "Modified By": ""}, {"Code": "MENI00030", "Title": "Financiers", "Icon": "", "Link": "/Masters/financiers", "Sequence": "51", "Click": "", "Menu": "MENU0003", "Submenu": "", "Permission": "Masters.view_financier", "Created On": "2022-11-05 13:13:08", "Modified On": "2023-01-10 13:06:42", "Created By": "", "Modified By": ""}, {"Code": "MENI00029", "Title": "Tenures", "Icon": "", "Link": "Masters/tenures/", "Sequence": "100", "Click": "", "Menu": "MENU0003", "Submenu": "", "Permission": "Masters.view_tenure", "Created On": "2022-11-05 13:13:08", "Modified On": "2023-01-10 13:06:42", "Created By": "", "Modified By": ""}, {"Code": "MENI00040", "Title": "Stock Transfer Approvals", "Icon": "FileProtectOutlined", "Link": "/pages/stock-transfer-approvals", "Sequence": "2", "Click": "", "Menu": "MENU0004", "Submenu": "SMENU0002", "Permission": "StockTransfer.approve_stocktransfer", "Created On": "2022-11-05 13:13:08", "Modified On": "2023-01-10 13:06:42", "Created By": "su", "Modified By": ""}, {"Code": "MENI00051", "Title": "Re-Estimation", "Icon": "OneToOneOutlined", "Link": "/Masters/Re-Estimation", "Sequence": "8", "Click": "", "Menu": "MENU0004", "Submenu": "", "Permission": "StockTransfer.view_reestimatonamount", "Created On": "2022-11-05 13:13:08", "Modified On": "2023-01-10 13:06:42", "Created By": "", "Modified By": ""}, {"Code": "MENI00046", "Title": "Insurance Agent", "Icon": "ProfileOutlined", "Link": "/pages/insurer", "Sequence": "10", "Click": "", "Menu": "MENU0004", "Submenu": "SMENU0003", "Permission": "InsuranceRto.agent_view_insurance", "Created On": "2022-11-05 13:13:08", "Modified On": "2023-01-10 13:06:42", "Created By": "", "Modified By": ""}, {"Code": "MENI00210", "Title": "VersionFeature", "Icon": "", "Link": "VersionFeature", "Sequence": "100", "Click": "1", "Menu": "MENU0007", "Submenu": "", "Permission": "Masters.import_versionfeature", "Created On": "2022-11-05 13:13:08", "Modified On": "2023-01-10 13:06:43", "Created By": "", "Modified By": ""}, {"Code": "MENI00209", "Title": "Version", "Icon": "", "Link": "Version", "Sequence": "100", "Click": "1", "Menu": "MENU0007", "Submenu": "", "Permission": "Masters.import_version", "Created On": "2022-11-05 13:13:08", "Modified On": "2023-01-10 13:06:43", "Created By": "", "Modified By": ""}, {"Code": "MENI00124", "Title": "Menuitem", "Icon": "", "Link": "Menuitem", "Sequence": "100", "Click": "", "Menu": "MENU0009", "Submenu": "", "Permission": "System.export_menuitem", "Created On": "2022-11-05 13:13:08", "Modified On": "2023-01-10 13:06:43", "Created By": "", "Modified By": ""}, {"Code": "MENI00039", "Title": "Enquiry", "Icon": "ContactsOutlined", "Link": "/pages/enquiry", "Sequence": "1", "Click": "", "Menu": "MENU0004", "Submenu": "SMENU0001", "Permission": "Purchase.view_enquiry", "Created On": "2022-11-05 13:13:08", "Modified On": "2023-01-10 13:06:43", "Created By": "", "Modified By": ""}, {"Code": "MENI00080", "Title": "Manage Profiles", "Icon": "", "Link": "/pages/settings/manage-profile", "Sequence": "2", "Click": "", "Menu": "MENU0008", "Submenu": "SMENU0007", "Permission": "auth.view_group", "Created On": "2022-11-05 13:13:08", "Modified On": "2023-01-10 13:06:43", "Created By": "", "Modified By": ""}, {"Code": "MENI00213", "Title": "Leave", "Icon": "", "Link": "/pages/report/Leave", "Sequence": "2", "Click": "", "Menu": "MENU0005", "Submenu": "", "Permission": "Attendance.reports_leave", "Created On": "2022-11-08 12:35:45", "Modified On": "2023-01-10 13:06:43", "Created By": "", "Modified By": ""}, {"Code": "MENI00054", "Title": "Daily Attendance", "Icon": "", "Link": "/pages/report/DailyAttendance", "Sequence": "1", "Click": "", "Menu": "MENU0005", "Submenu": "", "Permission": "Attendance.reports_dailyattendance", "Created On": "2022-11-05 13:13:08", "Modified On": "2023-01-10 13:06:43", "Created By": "", "Modified By": ""}, {"Code": "MENI00035", "Title": "Purchases", "Icon": "BarChartOutlined", "Link": "/pages/purchases", "Sequence": "2", "Click": "", "Menu": "MENU0004", "Submenu": "SMENU0001", "Permission": "Purchase.view_purchase", "Created On": "2022-11-05 13:13:08", "Modified On": "2023-01-10 13:06:43", "Created By": "", "Modified By": ""}, {"Code": "MENI00055", "Title": "Sale", "Icon": "", "Link": "/pages/report/Sale", "Sequence": "4", "Click": "", "Menu": "MENU0005", "Submenu": "", "Permission": "Sale.reports_sale", "Created On": "2022-11-05 13:13:08", "Modified On": "2023-01-10 13:06:43", "Created By": "", "Modified By": ""}, {"Code": "MENI00056", "Title": "Purchase", "Icon": "", "Link": "/pages/report/Purchase", "Sequence": "2", "Click": "", "Menu": "MENU0005", "Submenu": "", "Permission": "Purchase.reports_purchase", "Created On": "2022-11-05 13:13:08", "Modified On": "2023-01-10 13:06:43", "Created By": "", "Modified By": ""}, {"Code": "MENI00057", "Title": "Stock", "Icon": "", "Link": "/pages/report/Stock", "Sequence": "3", "Click": "", "Menu": "MENU0005", "Submenu": "", "Permission": "StockTransfer.reports_stocktransfer", "Created On": "2022-11-05 13:13:08", "Modified On": "2023-01-10 13:06:43", "Created By": "", "Modified By": ""}, {"Code": "MENI00058", "Title": "Repair Vehicles", "Icon": "", "Link": "/pages/report/RepairVechicle", "Sequence": "10", "Click": "", "Menu": "MENU0005", "Submenu": "", "Permission": "StockTransfer.reports_repairvechicle", "Created On": "2022-11-05 13:13:08", "Modified On": "2023-01-10 13:06:43", "Created By": "", "Modified By": ""}, {"Code": "MENI00059", "Title": "Temporary Transfer", "Icon": "", "Link": "/pages/report/TempraroryTransfer", "Sequence": "14", "Click": "", "Menu": "MENU0005", "Submenu": "", "Permission": "StockTransfer.reports_temprarorytransfer", "Created On": "2022-11-05 13:13:08", "Modified On": "2023-01-10 13:06:43", "Created By": "", "Modified By": ""}, {"Code": "MENI00060", "Title": "Enquiry", "Icon": "", "Link": "/pages/report/Enquiry", "Sequence": "6", "Click": "", "Menu": "MENU0005", "Submenu": "", "Permission": "Purchase.reports_enquiry", "Created On": "2022-11-05 13:13:08", "Modified On": "2023-01-10 13:06:43", "Created By": "", "Modified By": ""}, {"Code": "MENI00061", "Title": "Sale Quotation", "Icon": "", "Link": "/pages/report/SaleQuotation", "Sequence": "5", "Click": "", "Menu": "MENU0005", "Submenu": "", "Permission": "Sale.reports_salequotation", "Created On": "2022-11-05 13:13:08", "Modified On": "2023-01-10 13:06:43", "Created By": "", "Modified By": ""}, {"Code": "MENI00077", "Title": "Repair Amount", "Icon": "", "Link": "/pages/report/RepairAmount", "Sequence": "9", "Click": "", "Menu": "MENU0005", "Submenu": "", "Permission": "StockTransfer.reports_repairamount", "Created On": "2022-11-05 13:13:08", "Modified On": "2023-01-10 13:06:43", "Created By": "", "Modified By": ""}, {"Code": "MENI00067", "Title": "Stock In/Out List", "Icon": "0xe136", "Link": "/counterTransferListView", "Sequence": "6", "Click": "/counterTransferListView", "Menu": "MENU0001", "Submenu": "SMENU0004", "Permission": "StockTransfer.view_stocktransfer", "Created On": "2022-11-05 13:13:08", "Modified On": "2023-01-10 13:06:43", "Created By": "", "Modified By": ""}, {"Code": "MENI00045", "Title": "Approve Insurance", "Icon": "FileDoneOutlined", "Link": "/pages/approve-insurance", "Sequence": "9", "Click": "", "Menu": "MENU0004", "Submenu": "SMENU0003", "Permission": "InsuranceRto.approve_insurance", "Created On": "2022-11-05 13:13:08", "Modified On": "2023-01-10 13:06:43", "Created By": "", "Modified By": ""}, {"Code": "MENI00044", "Title": "New Insurance", "Icon": "FileTextOutlined", "Link": "/pages/new-insurance", "Sequence": "8", "Click": "", "Menu": "MENU0004", "Submenu": "SMENU0003", "Permission": "InsuranceRto.view_insurance", "Created On": "2022-11-05 13:13:08", "Modified On": "2023-01-10 13:06:43", "Created By": "", "Modified By": ""}, {"Code": "MENI00050", "Title": "Repair Amount", "Icon": "ToolOutlined", "Link": "/Masters/Repair-Amount", "Sequence": "7", "Click": "", "Menu": "MENU0004", "Submenu": "", "Permission": "StockTransfer.view_repairamount", "Created On": "2022-11-05 13:13:08", "Modified On": "2023-01-10 13:06:43", "Created By": "", "Modified By": ""}, {"Code": "MENI00043", "Title": "Temporary Transfers", "Icon": "ContactsOutlined", "Link": "/pages/stock-transfer-temprarory", "Sequence": "6", "Click": "", "Menu": "MENU0004", "Submenu": "SMENU0002", "Permission": "StockTransfer.view_temprarorytransfer", "Created On": "2022-11-05 13:13:08", "Modified On": "2023-01-10 13:06:43", "Created By": "", "Modified By": ""}, {"Code": "MENI00048", "Title": "Transaction Approvals", "Icon": "FileSyncOutlined", "Link": "/pages/transaction-approvals", "Sequence": "2", "Click": "", "Menu": "MENU0004", "Submenu": "", "Permission": "System.view_trans_approvals", "Created On": "2022-11-05 13:13:08", "Modified On": "2023-01-10 13:06:43", "Created By": "", "Modified By": ""}, {"Code": "MENI00049", "Title": "Reports", "Icon": "FileSyncOutlined", "Link": "/pages/reports/", "Sequence": "17", "Click": "", "Menu": "MENU0004", "Submenu": "", "Permission": "System.view_report", "Created On": "2022-11-05 13:13:08", "Modified On": "2023-01-10 13:06:43", "Created By": "", "Modified By": ""}, {"Code": "MENI00041", "Title": "Stock Transfer", "Icon": "FileSyncOutlined", "Link": "/pages/stock-in-out", "Sequence": "1", "Click": "", "Menu": "MENU0004", "Submenu": "SMENU0002", "Permission": "StockTransfer.view_stocktransfer", "Created On": "2022-11-05 13:13:08", "Modified On": "2023-01-10 13:06:43", "Created By": "", "Modified By": ""}, {"Code": "MENI00001", "Title": "Country", "Icon": "", "Link": "/Masters/country", "Sequence": "1", "Click": "", "Menu": "MENU0003", "Submenu": "", "Permission": "Masters.view_country", "Created On": "2022-11-05 13:13:09", "Modified On": "2023-01-10 13:06:43", "Created By": "", "Modified By": ""}, {"Code": "MENI00217", "Title": "User", "Icon": "", "Link": "User", "Sequence": "100", "Click": "", "Menu": "MENU0009", "Submenu": "", "Permission": "Users.export_user", "Created On": "2022-11-09 07:17:50", "Modified On": "2023-01-10 13:06:43", "Created By": "", "Modified By": ""}, {"Code": "MENI00212", "Title": "Vehicles", "Icon": "CarOutlined", "Link": "/Masters/vehicles", "Sequence": "12", "Click": "", "Menu": "MENU0004", "Submenu": "", "Permission": "Masters.view_vehicle", "Created On": "2022-11-05 13:13:08", "Modified On": "2023-01-10 13:06:43", "Created By": "", "Modified By": ""}, {"Code": "MENI00216", "Title": "Stock Transfer In", "Icon": "", "Link": "/pages/report/stock-transfer-in", "Sequence": "11", "Click": "", "Menu": "MENU0005", "Submenu": "", "Permission": "StockTransfer.reports_stocktransfer", "Created On": "2022-11-08 12:40:26", "Modified On": "2023-01-10 13:06:43", "Created By": "", "Modified By": ""}, {"Code": "MENI00215", "Title": "Stock Transfer Out", "Icon": "", "Link": "/pages/report/stock-transfer-out", "Sequence": "12", "Click": "", "Menu": "MENU0005", "Submenu": "", "Permission": "StockTransfer.reports_stocktransfer", "Created On": "2022-11-08 12:38:12", "Modified On": "2023-01-10 13:06:43", "Created By": "", "Modified By": ""}, {"Code": "MENI00078", "Title": "Re-Estimation Amount", "Icon": "", "Link": "/pages/report/RE-Amount", "Sequence": "8", "Click": "", "Menu": "MENU0005", "Submenu": "", "Permission": "StockTransfer.reports_reestimatonamount", "Created On": "2022-11-05 13:13:08", "Modified On": "2023-01-10 13:06:43", "Created By": "", "Modified By": ""}]